cchooks/__init__.py
cchooks/exceptions.py
cchooks/output_utils.py
cchooks/types.py
cchooks/utils.py
cchooks/contexts/__init__.py
cchooks/contexts/base.py
cchooks/contexts/notification.py
cchooks/contexts/post_tool_use.py
cchooks/contexts/pre_compact.py
cchooks/contexts/pre_tool_use.py
cchooks/contexts/session_end.py
cchooks/contexts/session_start.py
cchooks/contexts/stop.py
cchooks/contexts/subagent_stop.py
cchooks/contexts/user_prompt_submit.py
cchooks-0.1.5.dist-info/licenses/LICENSE
cchooks-0.1.5.dist-info/METADATA
cchooks-0.1.5.dist-info/WHEEL
cchooks-0.1.5.dist-info/top_level.txt
cchooks-0.1.5.dist-info/RECORD
